vocode/__init__.py
vocode/client.py
vocode/core/__init__.py
vocode/core/api_error.py
vocode/core/datetime_utils.py
vocode/core/jsonable_encoder.py
vocode/core/remove_none_from_headers.py
vocode/environment.py
vocode/errors/__init__.py
vocode/errors/unprocessable_entity_error.py
vocode/py.typed
vocode/resources/__init__.py
vocode/resources/actions/__init__.py
vocode/resources/actions/client.py
vocode/resources/agents/__init__.py
vocode/resources/agents/client.py
vocode/resources/calls/__init__.py
vocode/resources/calls/client.py
vocode/resources/numbers/__init__.py
vocode/resources/numbers/client.py
vocode/resources/usage/__init__.py
vocode/resources/usage/client.py
vocode/resources/voices/__init__.py
vocode/resources/voices/client.py
vocode/resources/webhooks/__init__.py
vocode/resources/webhooks/client.py
vocode/types/__init__.py
vocode/types/action_config.py
vocode/types/action_type.py
vocode/types/agent.py
vocode/types/agent_actions_item.py
vocode/types/agent_params.py
vocode/types/agent_params_actions_item.py
vocode/types/agent_params_voice.py
vocode/types/agent_params_webhook.py
vocode/types/agent_update_params.py
vocode/types/agent_update_params_actions.py
vocode/types/agent_update_params_actions_agent_update_params_actions_item.py
vocode/types/agent_update_params_initial_message.py
vocode/types/agent_update_params_prompt.py
vocode/types/agent_update_params_voice.py
vocode/types/agent_update_params_webhook.py
vocode/types/agent_voice.py
vocode/types/agent_webhook.py
vocode/types/azure_voice.py
vocode/types/azure_voice_params.py
vocode/types/azure_voice_update_params.py
vocode/types/azure_voice_update_params_pitch.py
vocode/types/azure_voice_update_params_rate.py
vocode/types/azure_voice_update_params_voice_name.py
vocode/types/call.py
vocode/types/call_agent.py
vocode/types/call_status.py
vocode/types/create_action_request.py
vocode/types/create_action_response.py
vocode/types/create_call_request_agent.py
vocode/types/create_voice_request.py
fern_vocode-0.0.4.dist-info/METADATA
fern_vocode-0.0.4.dist-info/WHEEL
fern_vocode-0.0.4.dist-info/RECORD
